pypai/__init__.py
pypai/pypai.py
pypai-1.3.dist-info/METADATA
pypai-1.3.dist-info/WHEEL
pypai-1.3.dist-info/top_level.txt
pypai-1.3.dist-info/RECORD
