Metadata-Version: 2.1
Name: pypai
Version: 1.3
Summary: The python tool for Open Platform for AI
Home-page: https://github.com/GeoffreyChen777/pypai
Author: Geoffrey CHen
Author-email: geoffreychen777@gmail.com
License: MIT
Platform: UNKNOWN
Requires-Dist: requests
Requires-Dist: pyhdfs
